ue5config/__init__.py
ue5config/config.py
ue5config/syntax.py
ue5config/uson.py
ue5config-0.0.3.dist-info/LICENSE
ue5config-0.0.3.dist-info/METADATA
ue5config-0.0.3.dist-info/WHEEL
ue5config-0.0.3.dist-info/RECORD
