Metadata-Version: 2.1
Name: ue5config
Version: 0.0.3
Summary: A grammatical parser for Unreal Engine 5 configuration files
Home-page: https://gitlab.com/N3X15/UE5Config
License: MIT
Author: Rob "N3X15" Nelson
Author-email: nexisentertainment@gmail.com
Requires-Python: >=3.8,<4.0
Classifier: License :: OSI Approved :: MIT License
Classifier: Programming Language :: Python :: 3
Classifier: Programming Language :: Python :: 3.8
Classifier: Programming Language :: Python :: 3.9
Classifier: Programming Language :: Python :: 3.10
Classifier: Programming Language :: Python :: 3.11
Requires-Dist: pyparsing (>=3.1.1,<4.0.0)
Project-URL: Repository, https://gitlab.com/N3X15/UE5Config.git
